<?xml version='1.0' ?>

<t:chloe xmlns:t="http://factorcode.org/chloe/1.0">

	<t:title>Planet Factor</t:title>

	<t:atom title="Planet Factor - Atom" href="feed.xml" />

	<t:style include="resource:extra/webapps/planet/planet.css" />

	<table width="100%" cellpadding="10">
		<tr>
			<td> <t:view component="postings" /> </td>

			<td valign="top" width="25%" class="infobox">
				<p>
					<strong>planet-factor</strong> is an Atom feed aggregator that collects the
					contents of <a href="http://factorcode.org/">Factor</a>-related blogs. It was inspired by
					<a href="http://planet.lisp.org">Planet Lisp</a>.
				</p>
				<p>
					<img src="http://planet.lisp.org/feed-icon-14x14.png" />
					<a href="feed.xml"> Syndicate </a>
				</p>

				<h2>Blogroll</h2>

				<t:summary component="blogroll" />

				Admin: <t:a href="edit-blog">Add Blog</t:a>
				|
				<t:a href="update">Update</t:a>
			</td>
		</tr>
	</table>

</t:chloe>
